sqlelf/__init__.py
sqlelf/__main__.py
sqlelf/_version.py
sqlelf/cli.py
sqlelf/elf.py
sqlelf/lief_ext.py
sqlelf/py.typed
sqlelf/sql.py
sqlelf/_vendor/elftools/METADATA
sqlelf/_vendor/elftools/__init__.py
sqlelf/_vendor/elftools/py.typed
sqlelf/_vendor/elftools/common/__init__.py
sqlelf/_vendor/elftools/common/construct_utils.py
sqlelf/_vendor/elftools/common/exceptions.py
sqlelf/_vendor/elftools/common/utils.py
sqlelf/_vendor/elftools/construct/LICENSE
sqlelf/_vendor/elftools/construct/README
sqlelf/_vendor/elftools/construct/__init__.py
sqlelf/_vendor/elftools/construct/adapters.py
sqlelf/_vendor/elftools/construct/core.py
sqlelf/_vendor/elftools/construct/debug.py
sqlelf/_vendor/elftools/construct/macros.py
sqlelf/_vendor/elftools/construct/lib/__init__.py
sqlelf/_vendor/elftools/construct/lib/binary.py
sqlelf/_vendor/elftools/construct/lib/bitstream.py
sqlelf/_vendor/elftools/construct/lib/container.py
sqlelf/_vendor/elftools/construct/lib/hex.py
sqlelf/_vendor/elftools/construct/lib/py3compat.py
sqlelf/_vendor/elftools/dwarf/__init__.py
sqlelf/_vendor/elftools/dwarf/abbrevtable.py
sqlelf/_vendor/elftools/dwarf/aranges.py
sqlelf/_vendor/elftools/dwarf/callframe.py
sqlelf/_vendor/elftools/dwarf/compileunit.py
sqlelf/_vendor/elftools/dwarf/constants.py
sqlelf/_vendor/elftools/dwarf/datatype_cpp.py
sqlelf/_vendor/elftools/dwarf/descriptions.py
sqlelf/_vendor/elftools/dwarf/die.py
sqlelf/_vendor/elftools/dwarf/dwarf_expr.py
sqlelf/_vendor/elftools/dwarf/dwarf_util.py
sqlelf/_vendor/elftools/dwarf/dwarfinfo.py
sqlelf/_vendor/elftools/dwarf/enums.py
sqlelf/_vendor/elftools/dwarf/lineprogram.py
sqlelf/_vendor/elftools/dwarf/locationlists.py
sqlelf/_vendor/elftools/dwarf/namelut.py
sqlelf/_vendor/elftools/dwarf/ranges.py
sqlelf/_vendor/elftools/dwarf/structs.py
sqlelf/_vendor/elftools/ehabi/__init__.py
sqlelf/_vendor/elftools/ehabi/constants.py
sqlelf/_vendor/elftools/ehabi/decoder.py
sqlelf/_vendor/elftools/ehabi/ehabiinfo.py
sqlelf/_vendor/elftools/ehabi/structs.py
sqlelf-0.5.dist-info/LICENSE
sqlelf-0.5.dist-info/METADATA
sqlelf-0.5.dist-info/WHEEL
sqlelf-0.5.dist-info/entry_points.txt
sqlelf-0.5.dist-info/top_level.txt
sqlelf-0.5.dist-info/RECORD
