Metadata-Version: 2.1
Name: sqlelf
Version: 0.5
Summary: Explore ELF objects through the power of SQL
Author-email: Farid Zakaria <farid.m.zakaria@gmail.com>
License: MIT License
Project-URL: Documentation, https://github.com/fzakaria/sqlelf#readme
Project-URL: Issues, https://github.com/fzakaria/sqlelf/issues
Project-URL: Source, https://github.com/fzakaria/sqlelf
Classifier: Development Status :: 4 - Beta
Classifier: Programming Language :: Python
Classifier: Programming Language :: Python :: 3.10
Classifier: Programming Language :: Python :: 3.11
Classifier: Programming Language :: Python :: Implementation :: CPython
Classifier: Programming Language :: Python :: Implementation :: PyPy
Requires-Python: <4.0,>=3.10
License-File: LICENSE
Requires-Dist: capstone >=5.0.1
Requires-Dist: lief >=0.14.1
Requires-Dist: apsw >=3.43.1.0
Requires-Dist: sh >=2.0.6
Provides-Extra: dev
Requires-Dist: black >=23.7.0 ; extra == 'dev'
Requires-Dist: isort >=5.12.0 ; extra == 'dev'
Requires-Dist: flake8 >=6.1.0 ; extra == 'dev'
Requires-Dist: flake8-print >=5.0.0 ; extra == 'dev'
Requires-Dist: pyright >=1.1.350 ; extra == 'dev'
Requires-Dist: pytest >=7.4.0 ; extra == 'dev'
Requires-Dist: mypy >=1.8.0 ; extra == 'dev'
Requires-Dist: coverage[toml] >=7.3 ; extra == 'dev'
